MANIFEST.in
README.md
requirements.txt
setup.cfg
setup.py
docs/analysis.md
docs/architecture.md
docs/faq.md
docs/index.md
docs/pipeline.md
docs/serving.md
docs/img/architecture.png
docs/img/web-app.png
examples/README.md
examples/app.py
examples/load_data.py
examples/train.py
examples/transform.py
examples/tune.py
examples/conf/trainer-cpu.yaml
examples/conf/trainer-memory.yaml
examples/conf/transformer.yaml
presto_query_predictor.egg-info/PKG-INFO
presto_query_predictor.egg-info/SOURCES.txt
presto_query_predictor.egg-info/dependency_links.txt
presto_query_predictor.egg-info/not-zip-safe
presto_query_predictor.egg-info/requires.txt
presto_query_predictor.egg-info/top_level.txt
query_predictor/__init__.py
query_predictor/conf/logging.conf
query_predictor/conf/serving.yaml
query_predictor/conf/trainer-cpu.yaml
query_predictor/conf/trainer-memory.yaml
query_predictor/conf/transformer.yaml
query_predictor/datasets/__init__.py
query_predictor/datasets/loader.py
query_predictor/datasets/data/tpch.csv
query_predictor/jupyter_notebooks/README.md
query_predictor/jupyter_notebooks/exploratory_analysis_presto_logs.ipynb
query_predictor/predictor/__init__.py
query_predictor/predictor/assembler.py
query_predictor/predictor/constant.py
query_predictor/predictor/data_loader.py
query_predictor/predictor/data_transformer.py
query_predictor/predictor/data_vectorizer.py
query_predictor/predictor/exceptions.py
query_predictor/predictor/label_creator.py
query_predictor/predictor/logging_utils.py
query_predictor/predictor/metadata.py
query_predictor/predictor/pipeline.py
query_predictor/predictor/predictor_app.py
query_predictor/predictor/version.py
query_predictor/predictor/classifier/__init__.py
query_predictor/predictor/classifier/classifier.py
query_predictor/predictor/classifier/classifier_factory.py
query_predictor/predictor/classifier/sklearn_classifier.py
query_predictor/predictor/classifier/xgboost_classifier.py
query_predictor/predictor/config/__init__.py
query_predictor/predictor/config/config_manager.py
query_predictor/predictor/config/config_validator.py
query_predictor/predictor/model/__init__.py
query_predictor/predictor/model/ml_model.py
query_predictor/predictor/model/model_manager.py
query_predictor/predictor/model/vectorizer_model.py
