Metadata-Version: 2.1
Name: presto-query-predictor
Version: 0.1.4
Summary: A query predictor pipeline and service to predict resource usages of Presto queries
Home-page: https://github.com/twitter-forks/presto/tree/query-predictor/presto-query-predictor
Author: Twitter Presto Team
Author-email: iq-dev@twitter.com
License: Apache 2.0
Keywords: presto sql ml
Platform: UNKNOWN
Classifier: Development Status :: 3 - Alpha
Classifier: Intended Audience :: Developers
Classifier: Intended Audience :: Science/Research
Classifier: License :: OSI Approved :: Apache Software License
Classifier: Operating System :: MacOS :: MacOS X
Classifier: Operating System :: POSIX
Classifier: Programming Language :: Python
Classifier: Programming Language :: Python :: 3
Classifier: Programming Language :: Python :: 3.7
Classifier: Programming Language :: Python :: 3.8
Classifier: Programming Language :: Python :: 3 :: Only
Classifier: Topic :: Database
Classifier: Topic :: Database :: Database Engines/Servers
Classifier: Topic :: Scientific/Engineering
Classifier: Topic :: Scientific/Engineering :: Artificial Intelligence
Classifier: Topic :: Software Development
Classifier: Topic :: Software Development :: Libraries
Requires-Python: >=3.7
Provides-Extra: tests
Provides-Extra: tutorial
